LICENSE
README.md
setup.py
leetcode/__init__.py
leetcode/api_client.py
leetcode/auth.py
leetcode/configuration.py
leetcode/rest.py
leetcode/api/__init__.py
leetcode/api/default_api.py
leetcode/models/__init__.py
leetcode/models/any_of_graphql_query_variables.py
leetcode/models/any_of_graphql_question_detail_solution.py
leetcode/models/base_submission_result.py
leetcode/models/difficulty.py
leetcode/models/graphql_data.py
leetcode/models/graphql_problemset_question_list.py
leetcode/models/graphql_query.py
leetcode/models/graphql_query_get_question_detail_variables.py
leetcode/models/graphql_query_problemset_question_list_variables.py
leetcode/models/graphql_query_problemset_question_list_variables_filter_input.py
leetcode/models/graphql_query_variables.py
leetcode/models/graphql_question_code_snippet.py
leetcode/models/graphql_question_contributor.py
leetcode/models/graphql_question_detail.py
leetcode/models/graphql_question_solution.py
leetcode/models/graphql_question_topic_tag.py
leetcode/models/graphql_response.py
leetcode/models/graphql_user.py
leetcode/models/id.py
leetcode/models/inline_response200.py
leetcode/models/interpretation.py
leetcode/models/one_ofid.py
leetcode/models/one_ofinline_response200.py
leetcode/models/problems.py
leetcode/models/stat.py
leetcode/models/stat_status_pair.py
leetcode/models/submission.py
leetcode/models/submission_id.py
leetcode/models/submission_result.py
leetcode/models/test_submission.py
leetcode/models/test_submission_result.py
python_leetcode.egg-info/PKG-INFO
python_leetcode.egg-info/SOURCES.txt
python_leetcode.egg-info/dependency_links.txt
python_leetcode.egg-info/requires.txt
python_leetcode.egg-info/top_level.txt
test/__init__.py
test/base.py
test/test_any_of_graphql_query_variables.py
test/test_any_of_graphql_question_detail_solution.py
test/test_base_submission_result.py
test/test_default_api.py
test/test_difficulty.py
test/test_graphql_data.py
test/test_graphql_problemset_question_list.py
test/test_graphql_query.py
test/test_graphql_query_get_question_detail_variables.py
test/test_graphql_query_problemset_question_list_variables.py
test/test_graphql_query_problemset_question_list_variables_filter_input.py
