Metadata-Version: 2.1
Name: python-leetcode
Version: 1.1.0
Summary: Leetcode API
Home-page: https://github.com/prius/python-leetcode
Author: Pavel Safronov
Author-email: pv.safronov@gmail.com
License: UNKNOWN
Keywords: leetcode,faang,interview,api
Platform: UNKNOWN
Classifier: Development Status :: 4 - Beta
Classifier: Intended Audience :: Developers
Classifier: Topic :: Software Development :: Libraries :: Python Modules
Classifier: License :: OSI Approved :: MIT License
Classifier: Programming Language :: Python :: 3
Classifier: Programming Language :: Python :: 3.8
Classifier: Programming Language :: Python :: 3.9
Requires-Python: >=3.8
License-File: LICENSE
